sqlalchemy_ibmi/__init__.py
sqlalchemy_ibmi/base.py
sqlalchemy_ibmi/constants.py
sqlalchemy_ibmi/requirements.py
sqlalchemy_ibmi-0.9.3.dist-info/LICENSE
sqlalchemy_ibmi-0.9.3.dist-info/METADATA
sqlalchemy_ibmi-0.9.3.dist-info/WHEEL
sqlalchemy_ibmi-0.9.3.dist-info/entry_points.txt
sqlalchemy_ibmi-0.9.3.dist-info/RECORD
