Metadata-Version: 2.1
Name: sqlalchemy-ibmi
Version: 0.9.3
Summary: SQLAlchemy support for Db2 on IBM i
License: Apache-2.0
Keywords: sqlalchemy,database,ibm,ibmi,db2
Author: Naveen Ram
Author-email: naveen.ram@ibm.com
Requires-Python: >=3.6.2
Classifier: Development Status :: 4 - Beta
Classifier: Intended Audience :: Developers
Classifier: License :: OSI Approved :: Apache Software License
Classifier: Operating System :: OS Independent
Classifier: Programming Language :: Python :: 3
Classifier: Programming Language :: Python :: 3.7
Classifier: Programming Language :: Python :: 3.8
Classifier: Programming Language :: Python :: 3.9
Classifier: Programming Language :: Python :: 3.10
Classifier: Programming Language :: Python :: 3.11
Classifier: Topic :: Database :: Front-Ends
Requires-Dist: pyodbc (>=4.0)
Requires-Dist: sqlalchemy (>=1.3.0,<2.0)
